{"time":98,"results":[{"type":"state-data-arrangement ","before":"\nstring public constant name = \"Bloom Coin\";\nstring public constant symbol = \"BLM\";\nuint8 public constant decimals = 8;\nuint256 public constant INITIAL_SUPPLY = 10 * 10**7 * (10**uint256(decimals));\nuint256 public weiRaised;\nuint256 public tokenAllocated;\naddress public owner;\nbool public saleToken = true;","after":"string public constant name = \"Bloom Coin\";\nstring public constant symbol = \"BLM\";\nuint256 public constant INITIAL_SUPPLY = 10 * 10**7 * (10**uint256(decimals));\nuint256 public weiRaised;\nuint256 public tokenAllocated;\naddress public owner;\nuint8 public constant decimals = 8;\nbool public saleToken = true;\n","contract":"BloomCoin","time":0}]}