{"time":24,"results":[{"type":"state-data-arrangement ","before":"\nstring public name = 'Refork';\nstring public symbol = 'EFK';\nuint8 public decimals = 18;\nuint256 public totalSupply;\naddress owner;\nmapping (address => uint256) public balanceOf;\nmapping (address => mapping (address => uint256)) public allowance;","after":"string public name = 'Refork';\nstring public symbol = 'EFK';\nuint256 public totalSupply;\nmapping (address => uint256) public balanceOf;\nmapping (address => mapping (address => uint256)) public allowance;\naddress owner;\nuint8 public decimals = 18;\n","contract":"TokenERC20","time":0},{"type":"constant-restrict-modification  ","before":"string public name = 'Refork';","after":"string public constant name = 'Refork';","contract":"TokenERC20","time":0},{"type":"constant-restrict-modification  ","before":"string public symbol = 'EFK';","after":"string public constant symbol = 'EFK';","contract":"TokenERC20","time":0},{"type":"constant-restrict-modification  ","before":"uint8 public decimals = 18;","after":"uint8 public constant decimals = 18;","contract":"TokenERC20","time":0}]}