{"time":59,"results":[{"type":"constant-restrict-modification  ","before":"string private _name = \"ANTEQUE\";","after":"string private constant _name = \"ANTEQUE\";","contract":"ERC20AntequeFreezable","time":0},{"type":"constant-restrict-modification  ","before":"string private _symbol = \"AQ\";","after":"string private constant _symbol = \"AQ\";","contract":"ERC20AntequeFreezable","time":0},{"type":"constant-restrict-modification  ","before":"uint8 private _decimals = 18;","after":"uint8 private constant _decimals = 18;","contract":"ERC20AntequeFreezable","time":0}]}