{"time":414,"results":[{"type":"state-data-arrangement ","before":"\nuint16 public MAX_SUPPLY = 12117;\nuint256 public presaleAccessCount = 0;\nuint16 _reservedCount = 111;\naddress _reservedTokensAddress;\nuint16 _maxPurchaseCount = 20;\nuint256 _mintPrice = 0.07 ether;\nuint256 _saleStart;\nuint256 _presaleStart;\nstring _baseURIValue;\nmapping(address => bool) _presaleAccess;\nmapping(address => bool) _canAddToPresale;","after":"uint256 public presaleAccessCount = 0;\nuint256 _mintPrice = 0.07 ether;\nuint256 _saleStart;\nuint256 _presaleStart;\nstring _baseURIValue;\nmapping(address => bool) _presaleAccess;\nmapping(address => bool) _canAddToPresale;\naddress _reservedTokensAddress;\nuint16 public MAX_SUPPLY = 12117;\nuint16 _reservedCount = 111;\nuint16 _maxPurchaseCount = 20;\n","contract":"AfroDroids","time":2}]}