{"time":65,"results":[{"type":"constant-restrict-modification  ","before":"uint public scale = 10 ** 18;","after":"uint public constant scale = 10 ** 18;","contract":"EminenceCurrency","time":0},{"type":"immutable-restrict-modification ","before":"uint32 public reserveRatio;","after":"uint32 public immutable reserveRatio;","contract":"EminenceCurrency","time":0},{"type":"immutable-restrict-modification ","before":"string private _name;","after":"string private immutable _name;","contract":"EminenceCurrency","time":0},{"type":"immutable-restrict-modification ","before":"string private _symbol;","after":"string private immutable _symbol;","contract":"EminenceCurrency","time":0},{"type":"immutable-restrict-modification ","before":"uint8 private _decimals;","after":"uint8 private immutable _decimals;","contract":"EminenceCurrency","time":0}]}