{"time":240,"results":[{"type":"constant-restrict-modification  ","before":"   bytes32 private immutable _DELEGATE_TYPEHASH =\n    keccak256(\"Delegate(address user,address delegate,uint256 nonce,uint256 deadline)","after":"   bytes32 private immutable constant _DELEGATE_TYPEHASH =\n    keccak256(\"Delegate(address user,address delegate,uint256 nonce,uint256 deadline)","contract":"Ticket","time":0},{"type":"constant-restrict-modification  ","before":"   bytes32 private immutable _PERMIT_TYPEHASH =\n    keccak256(\"Permit(address owner,address spender,uint256 value,uint256 nonce,uint256 deadline)","after":"   bytes32 private immutable constant _PERMIT_TYPEHASH =\n    keccak256(\"Permit(address owner,address spender,uint256 value,uint256 nonce,uint256 deadline)","contract":"Ticket","time":0},{"type":"immutable-restrict-modification ","before":"   string private _na","after":"   string private _na","contract":"Ticket","time":0},{"type":"immutable-restrict-modification ","before":"   string private _symb","after":"   string private _symb","contract":"Ticket","time":0}]}