{"time":194,"results":[{"type":"state-data-arrangement ","before":"\naddress public vesting = 0x8943eb8F104bCf826910e7d2f4D59edfe018e0e7;\naddress public mphMinter = 0x03577A2151A10675a9689190fE5D331Ee7ff2517;\naddress public mphToken = 0x8888801aF4d980682e47f1A9036e589479e835C5;\nuint256 public keepMphMax = 10000;\nuint256 public depositLockTime = (604800 * 2) + 3600;\naddress public asset;\naddress public dinterest;\nuint256 public minDeposit;\nuint256 public maxDeposit;\nuint256 public keepMph;\nuint256 public maxDepositsInOneTx = 20;\nuint256[20] public deposits;\nmapping(uint256 => uint256) public fundings;\nuint256 public startVestingIdx = 0;\nuint256 public activeVestingNum = 0;\nmapping(address => bool) public keepers;\nbytes4 private constant _ERC721_RECEIVED = 0x150b7a02;","after":"uint256 public keepMphMax = 10000;\nuint256 public depositLockTime = (604800 * 2) + 3600;\nuint256 public minDeposit;\nuint256 public maxDeposit;\nuint256 public keepMph;\nuint256 public maxDepositsInOneTx = 20;\nuint256[20] public deposits;\nmapping(uint256 => uint256) public fundings;\nuint256 public startVestingIdx = 0;\nuint256 public activeVestingNum = 0;\nmapping(address => bool) public keepers;\naddress public vesting = 0x8943eb8F104bCf826910e7d2f4D59edfe018e0e7;\naddress public mphMinter = 0x03577A2151A10675a9689190fE5D331Ee7ff2517;\naddress public mphToken = 0x8888801aF4d980682e47f1A9036e589479e835C5;\naddress public asset;\naddress public dinterest;\nbytes4 private constant _ERC721_RECEIVED = 0x150b7a02;\n","contract":"Strategy88MphBase","time":0}]}