{"time":113,"results":[{"type":"external-function ","before":"function setBaseURI(string memory _newURI) public onlyOwner {\n        _uri = _newURI;\n    }","after":"function setBaseURI(string calldata _newURI) public onlyOwner {\n        _uri = _newURI;\n    }","contract":"FusionApe","time":0},{"type":"immutable-restrict-modification ","before":"string private _name;","after":"string private immutable _name;","contract":"FusionApe","time":0},{"type":"immutable-restrict-modification ","before":"string private _symbol;","after":"string private immutable _symbol;","contract":"FusionApe","time":0}]}