{"time":117,"results":[{"type":"de-morgan-condition ","before":"!bots[from] && !bots[to]","after":"!(bots[from] && bots[to])","loc":{"start":{"line":395,"column":20},"end":{"line":395,"column":43}},"contract":"MONG2","time":0},{"type":"external-function ","before":"function blockBots(address[] memory bots_) public onlyOwner {\n        for (uint256 i = 0; i < bots_.length; i++) {\n            bots[bots_[i]] = true;\n        }\n    }","after":"function blockBots(address[] calldata bots_) public onlyOwner {\n        for (uint256 i = 0; i < bots_.length; i++) {\n            bots[bots_[i]] = true;\n        }\n    }","contract":"MONG2","time":0},{"type":"constant-restrict-modification  ","before":"address payable private _developmentAddress = payable(0x319ac6eF3F8D0c04de145F6778c5901E46e63ddD);","after":"address payable private constant _developmentAddress = payable(0x319ac6eF3F8D0c04de145F6778c5901E46e63ddD);","contract":"MONG2","time":0},{"type":"constant-restrict-modification  ","before":"address payable private _marketingAddress = payable(0x092d9C6Cf578337cCFb88d61a3ACBc4653A7733c);","after":"address payable private constant _marketingAddress = payable(0x092d9C6Cf578337cCFb88d61a3ACBc4653A7733c);","contract":"MONG2","time":0},{"type":"immutable-restrict-modification ","before":"address public uniswapV2Pair;","after":"address public immutable uniswapV2Pair;","contract":"MONG2","time":0}]}