{"time":98,"results":[{"type":"external-function ","before":"function setURI(string memory _URI) public onlyOwner {\n        URI = _URI;\n    }","after":"function setURI(string calldata _URI) public onlyOwner {\n        URI = _URI;\n    }","contract":"TycoonApes","time":0},{"type":"external-function ","before":"function setAllowedCollections(bool[] memory _allowedCollections) public onlyOwner {\n        allowedCollections = _allowedCollections;\n    }","after":"function setAllowedCollections(bool[] calldata _allowedCollections) public onlyOwner {\n        allowedCollections = _allowedCollections;\n    }","contract":"TycoonApes","time":0}]}