{"time":193,"results":[{"type":"immutable-restrict-modification ","before":"address public lootAddress;","after":"address public immutable lootAddress;","contract":"LootForCyberpunks","time":0},{"type":"immutable-restrict-modification ","before":"address public syntheticLootAddress;","after":"address public immutable syntheticLootAddress;","contract":"LootForCyberpunks","time":0},{"type":"immutable-restrict-modification ","before":"address public multisigAddress;","after":"address public immutable multisigAddress;","contract":"LootForCyberpunks","time":0}]}