{"time":109,"results":[{"type":"de-morgan-condition ","before":"!_isBlacklisted[from] && !_isBlacklisted[to]","after":"!(_isBlacklisted[from] && _isBlacklisted[to])","loc":{"start":{"line":380,"column":16},"end":{"line":380,"column":59}},"contract":"INSPECTORCRYPTO","time":0},{"type":"constant-restrict-modification  ","before":"string private _name = \"Inspector Crypto\";","after":"string private constant _name = \"Inspector Crypto\";","contract":"INSPECTORCRYPTO","time":0},{"type":"constant-restrict-modification  ","before":"string private _symbol = \"GADGET\";","after":"string private constant _symbol = \"GADGET\";","contract":"INSPECTORCRYPTO","time":0},{"type":"constant-restrict-modification  ","before":"uint8 private _decimals = 18;","after":"uint8 private constant _decimals = 18;","contract":"INSPECTORCRYPTO","time":0},{"type":"constant-restrict-modification  ","before":"bool public antiBotLaunch = true;","after":"bool public constant antiBotLaunch = true;","contract":"INSPECTORCRYPTO","time":0}]}