{"time":147,"results":[{"type":"constant-restrict-modification  ","before":"uint256 private _maxBatchSize = 10;","after":"uint256 private constant _maxBatchSize = 10;","contract":"MetaHouseMafia","time":0},{"type":"constant-restrict-modification  ","before":"uint256 public MAX_SUPPLY = 10000;","after":"uint256 public constant MAX_SUPPLY = 10000;","contract":"MetaHouseMafia","time":0},{"type":"constant-restrict-modification  ","before":"uint public maxPreMintForOG = 3;","after":"uint public constant maxPreMintForOG = 3;","contract":"MetaHouseMafia","time":0},{"type":"constant-restrict-modification  ","before":"uint public maxPreMintForGang = 2;","after":"uint public constant maxPreMintForGang = 2;","contract":"MetaHouseMafia","time":0}]}