{"time":64,"results":[{"type":"constant-restrict-modification  ","before":"uint256 public wellnessTreasuryTokens = 12_000_000;","after":"uint256 public constant wellnessTreasuryTokens = 12_000_000;","contract":"Wellness","time":0},{"type":"constant-restrict-modification  ","before":"address public wellnessTreasuryAddress=0x115d31069df4A47330803e1895697a5972bf478d;","after":"address public constant wellnessTreasuryAddress=0x115d31069df4A47330803e1895697a5972bf478d;","contract":"Wellness","time":0},{"type":"immutable-restrict-modification ","before":"uint256 decimalFactor;","after":"uint256 immutable decimalFactor;","contract":"Wellness","time":0}]}