{"time":168,"results":[{"type":"external-function ","before":"function addAllowList(address[] memory lists, uint256 limit)\n        public\n        onlyOwner\n    {\n        for (uint256 i; i < lists.length; i++) {\n            if (!_allowList.contains(lists[i])) {\n                _allowList.add(lists[i]);\n                _preSaleCounts[lists[i]] = limit;\n            }\n        }\n    }","after":"function addAllowList(address[] calldata lists, uint256 limit)\n        public\n        onlyOwner\n    {\n        for (uint256 i; i < lists.length; i++) {\n            if (!_allowList.contains(lists[i])) {\n                _allowList.add(lists[i]);\n                _preSaleCounts[lists[i]] = limit;\n            }\n        }\n    }","contract":"YakuzaCatsSociety","time":0},{"type":"external-function ","before":"function updateMetadata(string memory metadata) public onlyOwner {\n        _metadata = metadata;\n    }","after":"function updateMetadata(string calldata metadata) public onlyOwner {\n        _metadata = metadata;\n    }","contract":"YakuzaCatsSociety","time":0},{"type":"constant-restrict-modification  ","before":"uint256 private _publicSaleStartPrice = 0.893 ether;","after":"uint256 private constant _publicSaleStartPrice = 0.893 ether;","contract":"YakuzaCatsSociety","time":1},{"type":"constant-restrict-modification  ","before":"uint256 private _downPriceDuration = 14400;","after":"uint256 private constant _downPriceDuration = 14400;","contract":"YakuzaCatsSociety","time":1}]}