{"time":339,"results":[{"type":"struct-data-arrangement ","before":"\nuint256 balance\nuint256 collateralRatio\nuint256 marginDebt\nuint256 positionBalance\nuint256 latestSnapshot\nuint256 openPositionFee\nuint256 minPositionUnitsAmount\nuint168 buyingPremiumFee\nuint168 buyingPremiumFeePercentage\nuint168 tokenAmountToOpenPosition\nuint256 maxPositionUnitsAmount\nuint16 cviValue","after":"uint256 balance\nuint256 collateralRatio\nuint256 marginDebt\nuint256 positionBalance\nuint256 latestSnapshot\nuint256 openPositionFee\nuint256 minPositionUnitsAmount\nuint256 maxPositionUnitsAmount\nuint168 buyingPremiumFee\nuint168 buyingPremiumFeePercentage\nuint168 tokenAmountToOpenPosition\nuint16 cviValue\n","contract":"PlatformV2","time":0}]}