{"time":141,"results":[{"type":"immutable-restrict-modification ","before":"uint256 public fundingTarget;","after":"uint256 public immutable fundingTarget;","contract":"JPEGVaultIcoV2","time":1},{"type":"immutable-restrict-modification ","before":"address payable private _wallet;","after":"address payable private immutable _wallet;","contract":"JPEGVaultIcoV2","time":1},{"type":"immutable-restrict-modification ","before":"address private oracleAddress;","after":"address private immutable oracleAddress;","contract":"JPEGVaultIcoV2","time":1},{"type":"immutable-restrict-modification ","before":"address private _admin;","after":"address private immutable _admin;","contract":"JPEGVaultIcoV2","time":1}]}