{"time":205,"results":[{"type":"external-function ","before":"function updateBaseImgUrl(string memory _url) external onlyOwner {\n        require(!isPermanent, \"TankNFT: All images are on ipfs\");\n        _baseImgUrl = _url;\n    }","after":"function updateBaseImgUrl(string calldata _url) external onlyOwner {\n        require(!isPermanent, \"TankNFT: All images are on ipfs\");\n        _baseImgUrl = _url;\n    }","contract":"TankNFT","time":0},{"type":"immutable-restrict-modification ","before":"address private _receiver;","after":"address private immutable _receiver;","contract":"TankNFT","time":1},{"type":"constant-restrict-modification  ","before":"uint16 public MAX_PRE_ID = FOUNDER_TANKS_COUNT + 3200;","after":"uint16 public constant MAX_PRE_ID = FOUNDER_TANKS_COUNT + 3200;","contract":"TankNFT","time":1}]}