{"time":117,"results":[{"type":"external-function ","before":"function setBaseURI(string memory baseURI_) external onlyOwner {\n        _baseURIExtended = baseURI_;\n    }","after":"function setBaseURI(string calldata baseURI_) external onlyOwner {\n        _baseURIExtended = baseURI_;\n    }","contract":"SquidDAONFT","time":0},{"type":"external-function ","before":"function setTokenURI(uint256 tokenId, string memory tokenURI_)\n        external\n        onlyOwner\n    {\n        _tokenURIs[tokenId] = tokenURI_;\n    }","after":"function setTokenURI(uint256 tokenId, string calldata tokenURI_)\n        external\n        onlyOwner\n    {\n        _tokenURIs[tokenId] = tokenURI_;\n    }","contract":"SquidDAONFT","time":0}]}