{"time":165,"results":[{"type":"immutable-restrict-modification ","before":"address payable public treasury;","after":"address payable public immutable treasury;","contract":"INCOOOM","time":0},{"type":"immutable-restrict-modification ","before":"address payable public fund;","after":"address payable public immutable fund;","contract":"INCOOOM","time":0},{"type":"immutable-restrict-modification ","before":"address public helper;","after":"address public immutable helper;","contract":"INCOOOM","time":0}]}