{"time":129,"results":[{"type":"state-data-arrangement ","before":"\nuint public constant MAX_TOKENS = 5555;\nuint public constant NUMBER_RESERVED_TOKENS = 50;\nuint256 public constant PRICE = 55500000000000000;\nbool public saleIsActive = false;\nbool public preSaleIsActive = false;\nuint public reservedTokensMinted = 0;\nuint public supply = 0;\nstring private _baseTokenURI;\naddress payable private recipient1 = payable(0x0F7961EE81B7cB2B859157E9c0D7b1A1D9D35A5D);","after":"uint public constant MAX_TOKENS = 5555;\nuint public constant NUMBER_RESERVED_TOKENS = 50;\nuint256 public constant PRICE = 55500000000000000;\nuint public reservedTokensMinted = 0;\nuint public supply = 0;\nstring private _baseTokenURI;\naddress payable private recipient1 = payable(0x0F7961EE81B7cB2B859157E9c0D7b1A1D9D35A5D);\nbool public saleIsActive = false;\nbool public preSaleIsActive = false;\n","contract":"EvilElvesClub","time":0},{"type":"external-function ","before":"function setBaseURI(string memory baseURI) external onlyOwner {\r\n        _setBaseURI(baseURI);\r\n    }","after":"function setBaseURI(string calldata baseURI) external onlyOwner {\r\n        _setBaseURI(baseURI);\r\n    }","contract":"EvilElvesClub","time":0},{"type":"constant-restrict-modification  ","before":"address payable private recipient1 = payable(0x0F7961EE81B7cB2B859157E9c0D7b1A1D9D35A5D);","after":"address payable private constant recipient1 = payable(0x0F7961EE81B7cB2B859157E9c0D7b1A1D9D35A5D);","contract":"EvilElvesClub","time":1}]}