{"time":91,"results":[{"type":"de-morgan-condition ","before":"!bots[from] && !bots[to]","after":"!(bots[from] && bots[to])","loc":{"start":{"line":345,"column":20},"end":{"line":345,"column":43}},"contract":"NookToken","time":0},{"type":"external-function ","before":"function blockBots(address[] memory bots_) public onlyOwner {\n        for (uint256 i = 0; i < bots_.length; i++) {\n            bots[bots_[i]] = true;\n        }\n    }","after":"function blockBots(address[] calldata bots_) public onlyOwner {\n        for (uint256 i = 0; i < bots_.length; i++) {\n            bots[bots_[i]] = true;\n        }\n    }","contract":"NookToken","time":0},{"type":"constant-restrict-modification  ","before":"address payable private _marketingAddress = payable(0xB95CE39f109eeFd183b55B7a3Dd4D128b9B1562F);","after":"address payable private constant _marketingAddress = payable(0xB95CE39f109eeFd183b55B7a3Dd4D128b9B1562F);","contract":"NookToken","time":0},{"type":"constant-restrict-modification  ","before":"address payable private _devAddress = payable(0x2AA6710f40985a0697FBd59b71F9249e5278030C);","after":"address payable private constant _devAddress = payable(0x2AA6710f40985a0697FBd59b71F9249e5278030C);","contract":"NookToken","time":0},{"type":"immutable-restrict-modification ","before":"address public uniswapV2Pair;","after":"address public immutable uniswapV2Pair;","contract":"NookToken","time":0}]}