{"time":92,"results":[{"type":"constant-restrict-modification  ","before":"uint256 public immutable BOBL_PER_SECOND_PER_ROWDY_ROO = 11574 gwei;","after":"uint256 public immutable constant BOBL_PER_SECOND_PER_ROWDY_ROO = 11574 gwei;","contract":"BOBLToken","time":1},{"type":"constant-restrict-modification  ","before":"uint256 public immutable BOBL_PER_SECOND_PER_RAGING_ROO = 34722 gwei;","after":"uint256 public immutable constant BOBL_PER_SECOND_PER_RAGING_ROO = 34722 gwei;","contract":"BOBLToken","time":1},{"type":"constant-restrict-modification  ","before":"uint256 public immutable BOBL_PER_SECOND_PER_ROYAL_ROO = 69444 gwei;","after":"uint256 public immutable constant BOBL_PER_SECOND_PER_ROYAL_ROO = 69444 gwei;","contract":"BOBLToken","time":1},{"type":"constant-restrict-modification  ","before":"uint32 public immutable GENESIS = 1641852000;","after":"uint32 public immutable constant GENESIS = 1641852000;","contract":"BOBLToken","time":1}]}