{"time":189,"results":[{"type":"immutable-restrict-modification ","before":"uint256 public bonusEndBlock;","after":"uint256 public immutable bonusEndBlock;","contract":"MasterChef","time":1},{"type":"immutable-restrict-modification ","before":"uint256 public sushiPerBlock;","after":"uint256 public immutable sushiPerBlock;","contract":"MasterChef","time":1},{"type":"immutable-restrict-modification ","before":"uint256 public startBlock;","after":"uint256 public immutable startBlock;","contract":"MasterChef","time":1}]}