{"time":91,"results":[{"type":"external-function ","before":"function setBaseURI(string memory _newuri) external returns(bool){\n     base = _newuri;\n     return true;\n    }","after":"function setBaseURI(string calldata _newuri) external returns(bool){\n     base = _newuri;\n     return true;\n    }","contract":"Bonzai","time":0},{"type":"constant-restrict-modification  ","before":"string revealUrl = \"https://gateway.pinata.cloud/ipfs/QmYGaJXUfpsiGaRmuk5RuYFXZtFB9hiXFTueLqePEGFFsv\";","after":"string constant revealUrl = \"https://gateway.pinata.cloud/ipfs/QmYGaJXUfpsiGaRmuk5RuYFXZtFB9hiXFTueLqePEGFFsv\";","contract":"Bonzai","time":0}]}