{"time":152,"results":[{"type":"external-function ","before":"function setBaseURI(string memory baseURI) public onlyOwner {\n        _setBaseURI(baseURI);\n    }","after":"function setBaseURI(string calldata baseURI) public onlyOwner {\n        _setBaseURI(baseURI);\n    }","contract":"AbstractLoot","time":0},{"type":"external-function ","before":"function setProvenance(string memory prov) public onlyOwner {\n        PROVENANCE = prov;\n    }","after":"function setProvenance(string calldata prov) public onlyOwner {\n        PROVENANCE = prov;\n    }","contract":"AbstractLoot","time":0},{"type":"constant-restrict-modification  ","before":"address public lootAddress = 0xFF9C1b15B16263C61d017ee9F65C50e4AE0113D7;","after":"address public constant lootAddress = 0xFF9C1b15B16263C61d017ee9F65C50e4AE0113D7;","contract":"AbstractLoot","time":1}]}