{"time":204,"results":[{"type":"constant-restrict-modification  ","before":"address DEAD = 0x000000000000000000000000000000000000dEaD;","after":"address constant DEAD = 0x000000000000000000000000000000000000dEaD;","contract":"BabyShibnobi","time":2},{"type":"constant-restrict-modification  ","before":"uint8 private _decimals = 9;","after":"uint8 private constant _decimals = 9;","contract":"BabyShibnobi","time":2},{"type":"constant-restrict-modification  ","before":"uint256 private _tTotal = 1000000000 * 10**_decimals;","after":"uint256 private constant _tTotal = 1000000000 * 10**_decimals;","contract":"BabyShibnobi","time":2},{"type":"constant-restrict-modification  ","before":"string private _name = \"Baby Shibnobi\";","after":"string private constant _name = \"Baby Shibnobi\";","contract":"BabyShibnobi","time":2},{"type":"constant-restrict-modification  ","before":"string private _symbol = \"BabyShinja\";","after":"string private constant _symbol = \"BabyShinja\";","contract":"BabyShibnobi","time":2}]}