{"time":111,"results":[{"type":"constant-restrict-modification  ","before":"address private OSProxyRegistry             = 0xa5409ec958C83C3f309868babACA7c86DCB077c1;","after":"address private constant OSProxyRegistry             = 0xa5409ec958C83C3f309868babACA7c86DCB077c1;","contract":"FlyFroogles","time":0},{"type":"constant-restrict-modification  ","before":"uint256 public maxSupply                    = 10001;","after":"uint256 public constant maxSupply                    = 10001;","contract":"FlyFroogles","time":0}]}