{"time":98,"results":[{"type":"de-morgan-condition ","before":"!bots[from] && !bots[to]","after":"!(bots[from] && bots[to])","loc":{"start":{"line":367,"column":20},"end":{"line":367,"column":43}},"contract":"Shibyutaka","time":0},{"type":"external-function ","before":"function blockBots(address[] memory bots_) public onlyOwner {\n        for (uint256 i = 0; i < bots_.length; i++) {\n            bots[bots_[i]] = true;\n        }\n    }","after":"function blockBots(address[] calldata bots_) public onlyOwner {\n        for (uint256 i = 0; i < bots_.length; i++) {\n            bots[bots_[i]] = true;\n        }\n    }","contract":"Shibyutaka","time":0},{"type":"constant-restrict-modification  ","before":"address payable private _developmentAddress = payable(0xe258A9AF83797504626326b275ADF72bE31375Df);","after":"address payable private constant _developmentAddress = payable(0xe258A9AF83797504626326b275ADF72bE31375Df);","contract":"Shibyutaka","time":0},{"type":"constant-restrict-modification  ","before":"address payable private _marketingAddress = payable(0x769be6C33579269270B9FEcDCc5117C8A5Ce342d);","after":"address payable private constant _marketingAddress = payable(0x769be6C33579269270B9FEcDCc5117C8A5Ce342d);","contract":"Shibyutaka","time":0},{"type":"constant-restrict-modification  ","before":"address payable private _treasuryAddress = payable(0x3c1E811472d4977eAB5669D7B5BBC24a66a06833);","after":"address payable private constant _treasuryAddress = payable(0x3c1E811472d4977eAB5669D7B5BBC24a66a06833);","contract":"Shibyutaka","time":0},{"type":"immutable-restrict-modification ","before":"address public uniswapV2Pair;","after":"address public immutable uniswapV2Pair;","contract":"Shibyutaka","time":0}]}