{"time":119,"results":[{"type":"external-function ","before":"function setBaseURI(string memory newUri) \r\n    public \r\n    onlyOwner {\r\n        baseUrl = newUri;\r\n    }","after":"function setBaseURI(string calldata newUri) \r\n    public \r\n    onlyOwner {\r\n        baseUrl = newUri;\r\n    }","contract":"MightyRaccoons","time":0},{"type":"constant-restrict-modification  ","before":"uint256 immutable public maxSupply = 9999;","after":"uint256 immutable public constant maxSupply = 9999;","contract":"MightyRaccoons","time":0},{"type":"constant-restrict-modification  ","before":"uint256 public allowedwhitePerAddress = 4;","after":"uint256 public constant allowedwhitePerAddress = 4;","contract":"MightyRaccoons","time":0},{"type":"constant-restrict-modification  ","before":"uint256 public allowedPerAddress = 8;","after":"uint256 public constant allowedPerAddress = 8;","contract":"MightyRaccoons","time":0},{"type":"constant-restrict-modification  ","before":"address racoon1 = 0x25BC9Da80bE03682ca671349e58274E5FF81469C;","after":"address constant racoon1 = 0x25BC9Da80bE03682ca671349e58274E5FF81469C;","contract":"MightyRaccoons","time":0},{"type":"constant-restrict-modification  ","before":"address racoon2 = 0x344789A5Ef3118B8eDAb4fFCF06455EB226A645F;","after":"address constant racoon2 = 0x344789A5Ef3118B8eDAb4fFCF06455EB226A645F;","contract":"MightyRaccoons","time":0},{"type":"constant-restrict-modification  ","before":"address racoon3 = 0xFFBEA927699c88C299E28dA765A77d3d2D4455dE;","after":"address constant racoon3 = 0xFFBEA927699c88C299E28dA765A77d3d2D4455dE;","contract":"MightyRaccoons","time":0},{"type":"constant-restrict-modification  ","before":"address racoon4 = 0x06C32a292fFb76a70d7Ec6b8Ef3E510Df33047bD;","after":"address constant racoon4 = 0x06C32a292fFb76a70d7Ec6b8Ef3E510Df33047bD;","contract":"MightyRaccoons","time":0}]}