{"time":256,"results":[{"type":"state-data-arrangement ","before":"\nstring public constant name = \"Cryptogs\";\nstring public constant symbol = \"POGS\";\nstring public constant purpose = \"ETHDenver\";\nstring public constant contact = \"https://cryptogs.io\";\nstring public constant author = \"Austin Thomas Griffith\";\nuint8 public constant FLIPPINESS = 64;\nuint8 public constant FLIPPINESSROUNDBONUS = 16;\nuint8 public constant TIMEOUTBLOCKS = 180;\nuint8 public constant BLOCKSUNTILCLEANUPSTACK=1;\nstring public ipfs;\naddress public slammerTime;\nItem[] private items;\nPack[] private packs;\nmapping (bytes32 => uint256) public tokensOfImage;\nuint256 nonce = 0;\nmapping (bytes32 => Stack) public stacks;\nmapping (bytes32 => bytes32) public stackCounter;\nmapping (bytes32 => bytes32) public counterOfStack;\nmapping (bytes32 => uint8) public mode;\nmapping (bytes32 => uint8) public round;\nmapping (bytes32 => uint32) public lastBlock;\nmapping (bytes32 => uint32) public commitBlock;\nmapping (bytes32 => address) public lastActor;\nmapping (bytes32 => uint256[10]) public mixedStack;\nmapping (bytes32 => bytes32) public commit;","after":"string public constant name = \"Cryptogs\";\nstring public constant symbol = \"POGS\";\nstring public constant purpose = \"ETHDenver\";\nstring public constant contact = \"https://cryptogs.io\";\nstring public constant author = \"Austin Thomas Griffith\";\nstring public ipfs;\nItem[] private items;\nPack[] private packs;\nmapping (bytes32 => uint256) public tokensOfImage;\nuint256 nonce = 0;\nmapping (bytes32 => Stack) public stacks;\nmapping (bytes32 => bytes32) public stackCounter;\nmapping (bytes32 => bytes32) public counterOfStack;\nmapping (bytes32 => uint8) public mode;\nmapping (bytes32 => uint8) public round;\nmapping (bytes32 => uint32) public lastBlock;\nmapping (bytes32 => uint32) public commitBlock;\nmapping (bytes32 => address) public lastActor;\nmapping (bytes32 => uint256[10]) public mixedStack;\nmapping (bytes32 => bytes32) public commit;\naddress public slammerTime;\nuint8 public constant FLIPPINESS = 64;\nuint8 public constant FLIPPINESSROUNDBONUS = 16;\nuint8 public constant TIMEOUTBLOCKS = 180;\nuint8 public constant BLOCKSUNTILCLEANUPSTACK=1;\n","contract":"Cryptogs","time":0}]}