{"time":90,"results":[{"type":"external-function ","before":"function setBaseURI(string memory _newBaseURI) external onlyOwner {\r\n        baseURI = _newBaseURI;\r\n    }","after":"function setBaseURI(string calldata _newBaseURI) external onlyOwner {\r\n        baseURI = _newBaseURI;\r\n    }","contract":"HawaiianLionsToken","time":0},{"type":"external-function ","before":"function setPlaceholderURI(string memory _newPlaceHolderURI) external onlyOwner {\r\n        placeholderURI = _newPlaceHolderURI;\r\n    }","after":"function setPlaceholderURI(string calldata _newPlaceHolderURI) external onlyOwner {\r\n        placeholderURI = _newPlaceHolderURI;\r\n    }","contract":"HawaiianLionsToken","time":0},{"type":"constant-restrict-modification  ","before":"address private sammyAddress = 0x8bffc7415B1F8ceA3BF9e1f36EBb2FF15d175CF5;","after":"address private constant sammyAddress = 0x8bffc7415B1F8ceA3BF9e1f36EBb2FF15d175CF5;","contract":"HawaiianLionsToken","time":0},{"type":"constant-restrict-modification  ","before":"address private commyAddress = 0x6716D41029631116c5245096c46b04aca47D0Bd0;","after":"address private constant commyAddress = 0x6716D41029631116c5245096c46b04aca47D0Bd0;","contract":"HawaiianLionsToken","time":0},{"type":"immutable-restrict-modification ","before":"address payable private devAddress;","after":"address payable private immutable devAddress;","contract":"HawaiianLionsToken","time":0}]}